LICENSE.txt
MANIFEST.in
README.md
setup.py
hdf5_to_tiff/__init__.py
hdf5_to_tiff/main.py
hdf5_to_tiff.egg-info/PKG-INFO
hdf5_to_tiff.egg-info/SOURCES.txt
hdf5_to_tiff.egg-info/dependency_links.txt
hdf5_to_tiff.egg-info/entry_points.txt
hdf5_to_tiff.egg-info/requires.txt
hdf5_to_tiff.egg-info/top_level.txt
hdf5_to_tiff/modules/__init__.py
hdf5_to_tiff/modules/exception_handler.py
hdf5_to_tiff/modules/pyqt_utils.py
hdf5_to_tiff/modules/viewerGUI.py